pdm_django/__init__.py
pdm_django/main.py
pdm_django-0.5.2.dist-info/entry_points.txt
pdm_django-0.5.2.dist-info/WHEEL
pdm_django-0.5.2.dist-info/METADATA
pdm_django-0.5.2.dist-info/license_files/LICENSE
pdm_django-0.5.2.dist-info/RECORD
