Metadata-Version: 2.1
Name: pdm-django
Version: 0.5.2
Summary: pdm shortcuts for Django projects
License: MIT
Author-email: Paul Bailey <paul@neutron.studio>
Requires-Python: >=3.7
Project-URL: homepage, https://github.com/neutron-sync/pdm-django
